{
  "parent": "minecraft:recipes/root",
  "criteria": {
    "has_plastic_stick_iron_hoe": {
      "conditions": {
        "items": [
          {
            "items": "advancedtools:plastic_stick_iron_hoe"
          }
        ]
      },
      "trigger": "minecraft:inventory_changed"
    },
    "has_the_recipe": {
      "conditions": {
        "recipe": "advancedtools:blasting/plastic_stick_iron_hoe"
      },
      "trigger": "minecraft:recipe_unlocked"
    }
  },
  "requirements": [
    [
      "has_the_recipe",
      "has_plastic_stick_iron_hoe"
    ]
  ],
  "rewards": {
    "recipes": [
      "advancedtools:blasting/plastic_stick_iron_hoe"
    ]
  }
}