{
  "parent": "minecraft:recipes/root",
  "criteria": {
    "has_the_recipe": {
      "conditions": {
        "recipe": "advancedtools:blasting/witherbone_stick_iron_pickaxe"
      },
      "trigger": "minecraft:recipe_unlocked"
    },
    "has_witherbone_stick_iron_pickaxe": {
      "conditions": {
        "items": [
          {
            "items": "advancedtools:witherbone_stick_iron_pickaxe"
          }
        ]
      },
      "trigger": "minecraft:inventory_changed"
    }
  },
  "requirements": [
    [
      "has_the_recipe",
      "has_witherbone_stick_iron_pickaxe"
    ]
  ],
  "rewards": {
    "recipes": [
      "advancedtools:blasting/witherbone_stick_iron_pickaxe"
    ]
  }
}