{
  "neoforge:conditions": [
    {
      "type": "neoforge:and",
      "values": [
        {
          "type": "neoforge:not",
          "value": {
            "type": "neoforge:tag_empty",
            "tag": "c:silver_tool_materials"
          }
        },
        {
          "type": "neoforge:not",
          "value": {
            "type": "neoforge:tag_empty",
            "tag": "c:rods/cobalt"
          }
        },
        {
          "type": "neoforge:or",
          "values": [
            {
              "type": "neoforge:not",
              "value": {
                "type": "neoforge:tag_empty",
                "tag": "c:ingots/silver"
              }
            }
          ]
        }
      ]
    }
  ],
  "type": "minecraft:crafting_shaped",
  "category": "equipment",
  "key": {
    "#": "#c:rods/cobalt",
    "X": "#c:silver_tool_materials"
  },
  "pattern": [
    "XX",
    "# ",
    "# "
  ],
  "result": {
    "count": 1,
    "id": "advancedtools:cobalt_stick_silver_hoe"
  }
}
