{
  "neoforge:conditions": [
    {
      "type": "neoforge:and",
      "values": [
        {
          "type": "neoforge:not",
          "value": {
            "type": "neoforge:tag_empty",
            "tag": "c:rods/fluorite"
          }
        },
        {
          "type": "neoforge:not",
          "value": {
            "type": "neoforge:tag_empty",
            "tag": "c:osmium_tool_materials"
          }
        }
      ]
    }
  ],
  "type": "minecraft:crafting_shaped",
  "category": "equipment",
  "key": {
    "#": "#c:rods/fluorite",
    "X": "#c:osmium_tool_materials"
  },
  "pattern": [
    "XX",
    "# ",
    "# "
  ],
  "result": {
    "count": 1,
    "id": "advancedtools:fluorite_stick_osmium_hoe"
  }
}