{
  "neoforge:conditions": [
    {
      "type": "neoforge:and",
      "values": [
        {
          "type": "neoforge:not",
          "value": {
            "type": "neoforge:tag_empty",
            "tag": "c:cobalt_tool_materials"
          }
        },
        {
          "type": "neoforge:not",
          "value": {
            "type": "neoforge:tag_empty",
            "tag": "c:rods/pink_slime"
          }
        },
        {
          "type": "neoforge:or",
          "values": [
            {
              "type": "neoforge:not",
              "value": {
                "type": "neoforge:tag_empty",
                "tag": "c:ingots/cobalt"
              }
            }
          ]
        }
      ]
    }
  ],
  "type": "minecraft:crafting_shaped",
  "category": "equipment",
  "key": {
    "#": "#c:rods/pink_slime",
    "X": "#c:cobalt_tool_materials"
  },
  "pattern": [
    "X",
    "#",
    "#"
  ],
  "result": {
    "count": 1,
    "id": "advancedtools:pinkslime_stick_cobalt_shovel"
  }
}
